{
    "MineralSite": [
        {
            "source_id": "https://api.cdr.land/v1/docs/documents",
            "record_id": "02d6305964fcc0985c41326e7b42443e6efc8786dd4cebf434f50cbeb2a5811153",
            "name": "NI 43-101 Technical Report for the Birch Project in North America dated October 2011.pdf",
            "location_info": {
                "location": "POINT(-121.353556 52.40625)",
                "crs": {
                    "normalized_uri": "https://minmod.isi.edu/resource/Q701",
                    "confidence": 1,
                    "source": "Inferlink Extraction v2"
                },
                "country": {
                    "normalized_uri": "https://minmod.isi.edu/resource/Q1038",
                    "observed_name": "Canada",
                    "confidence": 1,
                    "source": "Inferlink Extraction v2"
                },
                "state_or_province": {
                    "normalized_uri": "https://minmod.isi.edu/resource/Q2654",
                    "observed_name": "British Columbia",
                    "confidence": 1,
                    "source": "Inferlink Extraction v2"
                }
            },
            "mineral_inventory": [
                {
                    "commodity": {
                        "normalized_uri": "https://minmod.isi.edu/resource/Q538",
                        "confidence": 1,
                        "source": "Inferlink Extraction v2"
                    },
                    "reference": {
                        "document": {
                            "title": "NI 43-101 Technical Report for the Birch Project in North America dated October 2011.pdf",
                            "authors": [
                                "J.W Morton"
                            ],
                            "year": 2011,
                            "month": 10,
                            "description": "This report provides an evaluation of the exploration potential of the Birch property, detailing the geology, past exploration, and recommended future exploration programs.",
                            "uri": "https://api.cdr.land/v1/docs/documents/02d6305964fcc0985c41326e7b42443e6efc8786dd4cebf434f50cbeb2a5811153"
                        }
                    },
                    "category": []
                }
            ],
            "deposit_type_candidate": [
                {
                    "observed_name": "alkalic porphyry copper and/or gold deposit",
                    "normalized_uri": "",
                    "source": "Inferlink Extraction v2",
                    "confidence": 1.0
                }
            ]
        }
    ]
}