{
    "MineralSite": [
        {
            "source_id": "https://api.cdr.land/v1/docs/documents",
            "record_id": "02df6bbca78257ce2e2bd47a455189e560508ad20fb695b32d1f882a99cd8badf0",
            "name": "NI 43-101 Technical Report for the Kinaskan Lake Project in North America dated May 2005.pdf",
            "location_info": {
                "location": "POINT(-130.25 57.6667)",
                "crs": {
                    "normalized_uri": "https://minmod.isi.edu/resource/Q701",
                    "confidence": 1,
                    "source": "Inferlink Extraction v2"
                },
                "country": {
                    "normalized_uri": "https://minmod.isi.edu/resource/Q1038",
                    "observed_name": "Canada",
                    "confidence": 1,
                    "source": "Inferlink Extraction v2"
                },
                "state_or_province": {
                    "normalized_uri": "https://minmod.isi.edu/resource/Q2654",
                    "observed_name": "British Columbia",
                    "confidence": 1,
                    "source": "Inferlink Extraction v2"
                }
            },
            "mineral_inventory": [
                {
                    "commodity": {
                        "normalized_uri": "https://minmod.isi.edu/resource/Q538",
                        "confidence": 1,
                        "source": "Inferlink Extraction v2"
                    },
                    "category": [
                        {
                            "normalized_uri": "https://minmod.isi.edu/resource/Inferred",
                            "confidence": 1,
                            "source": "Inferlink Extraction v2"
                        }
                    ],
                    "ore": {
                        "unit": {
                            "normalized_uri": "https://minmod.isi.edu/resource/Q202",
                            "observed_name": "million tonnes",
                            "confidence": 1,
                            "source": "Inferlink Extraction v2"
                        },
                        "value": 23.32
                    },
                    "grade": {
                        "unit": {
                            "normalized_uri": "https://minmod.isi.edu/resource/Q217",
                            "observed_name": "grams/tonne",
                            "confidence": 1,
                            "source": "Inferlink Extraction v2"
                        },
                        "value": 0.5
                    },
                    "cutoff_grade": {
                        "unit": {
                            "normalized_uri": "https://minmod.isi.edu/resource/Q204",
                            "observed_name": "percent Cu",
                            "confidence": 1,
                            "source": "Inferlink Extraction v2"
                        },
                        "value": 0.05
                    },
                    "contained_metal": 0.1166,
                    "reference": {
                        "document": {
                            "title": "NI 43-101 Technical Report for the Kinaskan Lake Project in North America dated May 2005.pdf",
                            "authors": [
                                "David T. Mehner",
                                "Giles R. Peatfield"
                            ],
                            "year": 2005,
                            "month": 5,
                            "description": "This technical report, prepared by consultants David T. Mehner and Giles R. Peatfield, provides an assessment of the Donnelly-GJ-North Copper-Gold Porphyry Zones in the Kinaskan Lake Project, including resource estimates and exploration recommendations.",
                            "uri": "https://api.cdr.land/v1/docs/documents/02df6bbca78257ce2e2bd47a455189e560508ad20fb695b32d1f882a99cd8badf0"
                        },
                        "page_info": [
                            {
                                "page": 50
                            }
                        ]
                    },
                    "date": "2005-5",
                    "zone": "sw sub-zone"
                },
                {
                    "commodity": {
                        "normalized_uri": "https://minmod.isi.edu/resource/Q538",
                        "confidence": 1,
                        "source": "Inferlink Extraction v2"
                    },
                    "category": [
                        {
                            "normalized_uri": "https://minmod.isi.edu/resource/Inferred",
                            "confidence": 1,
                            "source": "Inferlink Extraction v2"
                        }
                    ],
                    "ore": {
                        "unit": {
                            "normalized_uri": "https://minmod.isi.edu/resource/Q202",
                            "observed_name": "million tonnes",
                            "confidence": 1,
                            "source": "Inferlink Extraction v2"
                        },
                        "value": 14.18
                    },
                    "grade": {
                        "unit": {
                            "normalized_uri": "https://minmod.isi.edu/resource/Q217",
                            "observed_name": "grams/tonne",
                            "confidence": 1,
                            "source": "Inferlink Extraction v2"
                        },
                        "value": 0.7
                    },
                    "cutoff_grade": {
                        "unit": {
                            "normalized_uri": "https://minmod.isi.edu/resource/Q204",
                            "observed_name": "percent Cu",
                            "confidence": 1,
                            "source": "Inferlink Extraction v2"
                        },
                        "value": 0.1
                    },
                    "contained_metal": 0.0993,
                    "reference": {
                        "document": {
                            "title": "NI 43-101 Technical Report for the Kinaskan Lake Project in North America dated May 2005.pdf",
                            "authors": [
                                "David T. Mehner",
                                "Giles R. Peatfield"
                            ],
                            "year": 2005,
                            "month": 5,
                            "description": "This technical report, prepared by consultants David T. Mehner and Giles R. Peatfield, provides an assessment of the Donnelly-GJ-North Copper-Gold Porphyry Zones in the Kinaskan Lake Project, including resource estimates and exploration recommendations.",
                            "uri": "https://api.cdr.land/v1/docs/documents/02df6bbca78257ce2e2bd47a455189e560508ad20fb695b32d1f882a99cd8badf0"
                        },
                        "page_info": [
                            {
                                "page": 50
                            }
                        ]
                    },
                    "date": "2005-5",
                    "zone": "sw sub-zone"
                },
                {
                    "commodity": {
                        "normalized_uri": "https://minmod.isi.edu/resource/Q538",
                        "confidence": 1,
                        "source": "Inferlink Extraction v2"
                    },
                    "category": [
                        {
                            "normalized_uri": "https://minmod.isi.edu/resource/Inferred",
                            "confidence": 1,
                            "source": "Inferlink Extraction v2"
                        }
                    ],
                    "ore": {
                        "unit": {
                            "normalized_uri": "https://minmod.isi.edu/resource/Q202",
                            "observed_name": "million tonnes",
                            "confidence": 1,
                            "source": "Inferlink Extraction v2"
                        },
                        "value": 11.26
                    },
                    "grade": {
                        "unit": {
                            "normalized_uri": "https://minmod.isi.edu/resource/Q217",
                            "observed_name": "grams/tonne",
                            "confidence": 1,
                            "source": "Inferlink Extraction v2"
                        },
                        "value": 0.8
                    },
                    "cutoff_grade": {
                        "unit": {
                            "normalized_uri": "https://minmod.isi.edu/resource/Q204",
                            "observed_name": "percent Cu",
                            "confidence": 1,
                            "source": "Inferlink Extraction v2"
                        },
                        "value": 0.15
                    },
                    "contained_metal": 0.0901,
                    "reference": {
                        "document": {
                            "title": "NI 43-101 Technical Report for the Kinaskan Lake Project in North America dated May 2005.pdf",
                            "authors": [
                                "David T. Mehner",
                                "Giles R. Peatfield"
                            ],
                            "year": 2005,
                            "month": 5,
                            "description": "This technical report, prepared by consultants David T. Mehner and Giles R. Peatfield, provides an assessment of the Donnelly-GJ-North Copper-Gold Porphyry Zones in the Kinaskan Lake Project, including resource estimates and exploration recommendations.",
                            "uri": "https://api.cdr.land/v1/docs/documents/02df6bbca78257ce2e2bd47a455189e560508ad20fb695b32d1f882a99cd8badf0"
                        },
                        "page_info": [
                            {
                                "page": 50
                            }
                        ]
                    },
                    "date": "2005-5",
                    "zone": "sw sub-zone"
                },
                {
                    "commodity": {
                        "normalized_uri": "https://minmod.isi.edu/resource/Q538",
                        "confidence": 1,
                        "source": "Inferlink Extraction v2"
                    },
                    "category": [
                        {
                            "normalized_uri": "https://minmod.isi.edu/resource/Inferred",
                            "confidence": 1,
                            "source": "Inferlink Extraction v2"
                        }
                    ],
                    "ore": {
                        "unit": {
                            "normalized_uri": "https://minmod.isi.edu/resource/Q202",
                            "observed_name": "million tonnes",
                            "confidence": 1,
                            "source": "Inferlink Extraction v2"
                        },
                        "value": 6.58
                    },
                    "grade": {
                        "unit": {
                            "normalized_uri": "https://minmod.isi.edu/resource/Q217",
                            "observed_name": "grams/tonne",
                            "confidence": 1,
                            "source": "Inferlink Extraction v2"
                        },
                        "value": 1.1
                    },
                    "cutoff_grade": {
                        "unit": {
                            "normalized_uri": "https://minmod.isi.edu/resource/Q204",
                            "observed_name": "percent Cu",
                            "confidence": 1,
                            "source": "Inferlink Extraction v2"
                        },
                        "value": 0.2
                    },
                    "contained_metal": 0.0724,
                    "reference": {
                        "document": {
                            "title": "NI 43-101 Technical Report for the Kinaskan Lake Project in North America dated May 2005.pdf",
                            "authors": [
                                "David T. Mehner",
                                "Giles R. Peatfield"
                            ],
                            "year": 2005,
                            "month": 5,
                            "description": "This technical report, prepared by consultants David T. Mehner and Giles R. Peatfield, provides an assessment of the Donnelly-GJ-North Copper-Gold Porphyry Zones in the Kinaskan Lake Project, including resource estimates and exploration recommendations.",
                            "uri": "https://api.cdr.land/v1/docs/documents/02df6bbca78257ce2e2bd47a455189e560508ad20fb695b32d1f882a99cd8badf0"
                        },
                        "page_info": [
                            {
                                "page": 50
                            }
                        ]
                    },
                    "date": "2005-5",
                    "zone": "sw sub-zone"
                },
                {
                    "commodity": {
                        "normalized_uri": "https://minmod.isi.edu/resource/Q538",
                        "confidence": 1,
                        "source": "Inferlink Extraction v2"
                    },
                    "category": [
                        {
                            "normalized_uri": "https://minmod.isi.edu/resource/Inferred",
                            "confidence": 1,
                            "source": "Inferlink Extraction v2"
                        }
                    ],
                    "ore": {
                        "unit": {
                            "normalized_uri": "https://minmod.isi.edu/resource/Q202",
                            "observed_name": "million tonnes",
                            "confidence": 1,
                            "source": "Inferlink Extraction v2"
                        },
                        "value": 5.19
                    },
                    "grade": {
                        "unit": {
                            "normalized_uri": "https://minmod.isi.edu/resource/Q217",
                            "observed_name": "grams/tonne",
                            "confidence": 1,
                            "source": "Inferlink Extraction v2"
                        },
                        "value": 1.1
                    },
                    "cutoff_grade": {
                        "unit": {
                            "normalized_uri": "https://minmod.isi.edu/resource/Q204",
                            "observed_name": "percent Cu",
                            "confidence": 1,
                            "source": "Inferlink Extraction v2"
                        },
                        "value": 0.25
                    },
                    "contained_metal": 0.0571,
                    "reference": {
                        "document": {
                            "title": "NI 43-101 Technical Report for the Kinaskan Lake Project in North America dated May 2005.pdf",
                            "authors": [
                                "David T. Mehner",
                                "Giles R. Peatfield"
                            ],
                            "year": 2005,
                            "month": 5,
                            "description": "This technical report, prepared by consultants David T. Mehner and Giles R. Peatfield, provides an assessment of the Donnelly-GJ-North Copper-Gold Porphyry Zones in the Kinaskan Lake Project, including resource estimates and exploration recommendations.",
                            "uri": "https://api.cdr.land/v1/docs/documents/02df6bbca78257ce2e2bd47a455189e560508ad20fb695b32d1f882a99cd8badf0"
                        },
                        "page_info": [
                            {
                                "page": 50
                            }
                        ]
                    },
                    "date": "2005-5",
                    "zone": "sw sub-zone"
                },
                {
                    "commodity": {
                        "normalized_uri": "https://minmod.isi.edu/resource/Q538",
                        "confidence": 1,
                        "source": "Inferlink Extraction v2"
                    },
                    "category": [
                        {
                            "normalized_uri": "https://minmod.isi.edu/resource/Inferred",
                            "confidence": 1,
                            "source": "Inferlink Extraction v2"
                        }
                    ],
                    "ore": {
                        "unit": {
                            "normalized_uri": "https://minmod.isi.edu/resource/Q202",
                            "observed_name": "million tonnes",
                            "confidence": 1,
                            "source": "Inferlink Extraction v2"
                        },
                        "value": 4.61
                    },
                    "grade": {
                        "unit": {
                            "normalized_uri": "https://minmod.isi.edu/resource/Q217",
                            "observed_name": "grams/tonne",
                            "confidence": 1,
                            "source": "Inferlink Extraction v2"
                        },
                        "value": 1.2
                    },
                    "cutoff_grade": {
                        "unit": {
                            "normalized_uri": "https://minmod.isi.edu/resource/Q204",
                            "observed_name": "percent Cu",
                            "confidence": 1,
                            "source": "Inferlink Extraction v2"
                        },
                        "value": 0.3
                    },
                    "contained_metal": 0.0553,
                    "reference": {
                        "document": {
                            "title": "NI 43-101 Technical Report for the Kinaskan Lake Project in North America dated May 2005.pdf",
                            "authors": [
                                "David T. Mehner",
                                "Giles R. Peatfield"
                            ],
                            "year": 2005,
                            "month": 5,
                            "description": "This technical report, prepared by consultants David T. Mehner and Giles R. Peatfield, provides an assessment of the Donnelly-GJ-North Copper-Gold Porphyry Zones in the Kinaskan Lake Project, including resource estimates and exploration recommendations.",
                            "uri": "https://api.cdr.land/v1/docs/documents/02df6bbca78257ce2e2bd47a455189e560508ad20fb695b32d1f882a99cd8badf0"
                        },
                        "page_info": [
                            {
                                "page": 50
                            }
                        ]
                    },
                    "date": "2005-5",
                    "zone": "sw sub-zone"
                },
                {
                    "commodity": {
                        "normalized_uri": "https://minmod.isi.edu/resource/Q538",
                        "confidence": 1,
                        "source": "Inferlink Extraction v2"
                    },
                    "category": [
                        {
                            "normalized_uri": "https://minmod.isi.edu/resource/Inferred",
                            "confidence": 1,
                            "source": "Inferlink Extraction v2"
                        }
                    ],
                    "ore": {
                        "unit": {
                            "normalized_uri": "https://minmod.isi.edu/resource/Q202",
                            "observed_name": "million tonnes",
                            "confidence": 1,
                            "source": "Inferlink Extraction v2"
                        },
                        "value": 2.3
                    },
                    "grade": {
                        "unit": {
                            "normalized_uri": "https://minmod.isi.edu/resource/Q217",
                            "observed_name": "grams/tonne",
                            "confidence": 1,
                            "source": "Inferlink Extraction v2"
                        },
                        "value": 1.6
                    },
                    "cutoff_grade": {
                        "unit": {
                            "normalized_uri": "https://minmod.isi.edu/resource/Q204",
                            "observed_name": "percent Cu",
                            "confidence": 1,
                            "source": "Inferlink Extraction v2"
                        },
                        "value": 0.35
                    },
                    "contained_metal": 0.0368,
                    "reference": {
                        "document": {
                            "title": "NI 43-101 Technical Report for the Kinaskan Lake Project in North America dated May 2005.pdf",
                            "authors": [
                                "David T. Mehner",
                                "Giles R. Peatfield"
                            ],
                            "year": 2005,
                            "month": 5,
                            "description": "This technical report, prepared by consultants David T. Mehner and Giles R. Peatfield, provides an assessment of the Donnelly-GJ-North Copper-Gold Porphyry Zones in the Kinaskan Lake Project, including resource estimates and exploration recommendations.",
                            "uri": "https://api.cdr.land/v1/docs/documents/02df6bbca78257ce2e2bd47a455189e560508ad20fb695b32d1f882a99cd8badf0"
                        },
                        "page_info": [
                            {
                                "page": 50
                            }
                        ]
                    },
                    "date": "2005-5",
                    "zone": "sw sub-zone"
                },
                {
                    "commodity": {
                        "normalized_uri": "https://minmod.isi.edu/resource/Q538",
                        "confidence": 1,
                        "source": "Inferlink Extraction v2"
                    },
                    "category": [
                        {
                            "normalized_uri": "https://minmod.isi.edu/resource/Inferred",
                            "confidence": 1,
                            "source": "Inferlink Extraction v2"
                        }
                    ],
                    "ore": {
                        "unit": {
                            "normalized_uri": "https://minmod.isi.edu/resource/Q202",
                            "observed_name": "million tonnes",
                            "confidence": 1,
                            "source": "Inferlink Extraction v2"
                        },
                        "value": 2.3
                    },
                    "grade": {
                        "unit": {
                            "normalized_uri": "https://minmod.isi.edu/resource/Q217",
                            "observed_name": "grams/tonne",
                            "confidence": 1,
                            "source": "Inferlink Extraction v2"
                        },
                        "value": 1.6
                    },
                    "cutoff_grade": {
                        "unit": {
                            "normalized_uri": "https://minmod.isi.edu/resource/Q204",
                            "observed_name": "percent Cu",
                            "confidence": 1,
                            "source": "Inferlink Extraction v2"
                        },
                        "value": 0.4
                    },
                    "contained_metal": 0.0368,
                    "reference": {
                        "document": {
                            "title": "NI 43-101 Technical Report for the Kinaskan Lake Project in North America dated May 2005.pdf",
                            "authors": [
                                "David T. Mehner",
                                "Giles R. Peatfield"
                            ],
                            "year": 2005,
                            "month": 5,
                            "description": "This technical report, prepared by consultants David T. Mehner and Giles R. Peatfield, provides an assessment of the Donnelly-GJ-North Copper-Gold Porphyry Zones in the Kinaskan Lake Project, including resource estimates and exploration recommendations.",
                            "uri": "https://api.cdr.land/v1/docs/documents/02df6bbca78257ce2e2bd47a455189e560508ad20fb695b32d1f882a99cd8badf0"
                        },
                        "page_info": [
                            {
                                "page": 50
                            }
                        ]
                    },
                    "date": "2005-5",
                    "zone": "sw sub-zone"
                },
                {
                    "commodity": {
                        "normalized_uri": "https://minmod.isi.edu/resource/Q538",
                        "confidence": 1,
                        "source": "Inferlink Extraction v2"
                    },
                    "category": [
                        {
                            "normalized_uri": "https://minmod.isi.edu/resource/Inferred",
                            "confidence": 1,
                            "source": "Inferlink Extraction v2"
                        }
                    ],
                    "ore": {
                        "unit": {
                            "normalized_uri": "https://minmod.isi.edu/resource/Q202",
                            "observed_name": "million tonnes",
                            "confidence": 1,
                            "source": "Inferlink Extraction v2"
                        },
                        "value": 20.63
                    },
                    "grade": {
                        "unit": {
                            "normalized_uri": "https://minmod.isi.edu/resource/Q217",
                            "observed_name": "grams/tonne",
                            "confidence": 1,
                            "source": "Inferlink Extraction v2"
                        },
                        "value": 1.1
                    },
                    "cutoff_grade": {
                        "unit": {
                            "normalized_uri": "https://minmod.isi.edu/resource/Q204",
                            "observed_name": "percent Cu",
                            "confidence": 1,
                            "source": "Inferlink Extraction v2"
                        },
                        "value": 0.05
                    },
                    "contained_metal": 0.2269,
                    "reference": {
                        "document": {
                            "title": "NI 43-101 Technical Report for the Kinaskan Lake Project in North America dated May 2005.pdf",
                            "authors": [
                                "David T. Mehner",
                                "Giles R. Peatfield"
                            ],
                            "year": 2005,
                            "month": 5,
                            "description": "This technical report, prepared by consultants David T. Mehner and Giles R. Peatfield, provides an assessment of the Donnelly-GJ-North Copper-Gold Porphyry Zones in the Kinaskan Lake Project, including resource estimates and exploration recommendations.",
                            "uri": "https://api.cdr.land/v1/docs/documents/02df6bbca78257ce2e2bd47a455189e560508ad20fb695b32d1f882a99cd8badf0"
                        }
                    },
                    "date": "2005-5",
                    "zone": "nw sub-zone"
                },
                {
                    "commodity": {
                        "normalized_uri": "https://minmod.isi.edu/resource/Q538",
                        "confidence": 1,
                        "source": "Inferlink Extraction v2"
                    },
                    "category": [
                        {
                            "normalized_uri": "https://minmod.isi.edu/resource/Inferred",
                            "confidence": 1,
                            "source": "Inferlink Extraction v2"
                        }
                    ],
                    "ore": {
                        "unit": {
                            "normalized_uri": "https://minmod.isi.edu/resource/Q202",
                            "observed_name": "million tonnes",
                            "confidence": 1,
                            "source": "Inferlink Extraction v2"
                        },
                        "value": 17.79
                    },
                    "grade": {
                        "unit": {
                            "normalized_uri": "https://minmod.isi.edu/resource/Q217",
                            "observed_name": "grams/tonne",
                            "confidence": 1,
                            "source": "Inferlink Extraction v2"
                        },
                        "value": 1.2
                    },
                    "cutoff_grade": {
                        "unit": {
                            "normalized_uri": "https://minmod.isi.edu/resource/Q204",
                            "observed_name": "percent Cu",
                            "confidence": 1,
                            "source": "Inferlink Extraction v2"
                        },
                        "value": 0.1
                    },
                    "contained_metal": 0.2135,
                    "reference": {
                        "document": {
                            "title": "NI 43-101 Technical Report for the Kinaskan Lake Project in North America dated May 2005.pdf",
                            "authors": [
                                "David T. Mehner",
                                "Giles R. Peatfield"
                            ],
                            "year": 2005,
                            "month": 5,
                            "description": "This technical report, prepared by consultants David T. Mehner and Giles R. Peatfield, provides an assessment of the Donnelly-GJ-North Copper-Gold Porphyry Zones in the Kinaskan Lake Project, including resource estimates and exploration recommendations.",
                            "uri": "https://api.cdr.land/v1/docs/documents/02df6bbca78257ce2e2bd47a455189e560508ad20fb695b32d1f882a99cd8badf0"
                        }
                    },
                    "date": "2005-5",
                    "zone": "nw sub-zone"
                },
                {
                    "commodity": {
                        "normalized_uri": "https://minmod.isi.edu/resource/Q551",
                        "confidence": 1,
                        "source": "Inferlink Extraction v2"
                    },
                    "category": [
                        {
                            "normalized_uri": "https://minmod.isi.edu/resource/Inferred",
                            "confidence": 1,
                            "source": "Inferlink Extraction v2"
                        }
                    ],
                    "material_form": {
                        "observed_name": "copper",
                        "confidence": 1,
                        "source": "Inferlink Extraction v2"
                    },
                    "ore": {
                        "unit": {
                            "normalized_uri": "https://minmod.isi.edu/resource/Q202",
                            "observed_name": "million tonnes",
                            "confidence": 1,
                            "source": "Inferlink Extraction v2"
                        },
                        "value": 124.92
                    },
                    "grade": {
                        "unit": {
                            "normalized_uri": "https://minmod.isi.edu/resource/Q201",
                            "observed_name": "percent",
                            "confidence": 1,
                            "source": "Inferlink Extraction v2"
                        },
                        "value": 0.28
                    },
                    "cutoff_grade": {
                        "unit": {
                            "normalized_uri": "https://minmod.isi.edu/resource/Q204",
                            "observed_name": "percent Cu",
                            "confidence": 1,
                            "source": "Inferlink Extraction v2"
                        },
                        "value": 0.05
                    },
                    "contained_metal": 0.3498,
                    "reference": {
                        "document": {
                            "title": "NI 43-101 Technical Report for the Kinaskan Lake Project in North America dated May 2005.pdf",
                            "authors": [
                                "David T. Mehner",
                                "Giles R. Peatfield"
                            ],
                            "year": 2005,
                            "month": 5,
                            "description": "This technical report, prepared by consultants David T. Mehner and Giles R. Peatfield, provides an assessment of the Donnelly-GJ-North Copper-Gold Porphyry Zones in the Kinaskan Lake Project, including resource estimates and exploration recommendations.",
                            "uri": "https://api.cdr.land/v1/docs/documents/02df6bbca78257ce2e2bd47a455189e560508ad20fb695b32d1f882a99cd8badf0"
                        }
                    },
                    "date": "2005-5",
                    "zone": "donnelly zone"
                },
                {
                    "commodity": {
                        "normalized_uri": "https://minmod.isi.edu/resource/Q551",
                        "confidence": 1,
                        "source": "Inferlink Extraction v2"
                    },
                    "category": [
                        {
                            "normalized_uri": "https://minmod.isi.edu/resource/Inferred",
                            "confidence": 1,
                            "source": "Inferlink Extraction v2"
                        }
                    ],
                    "material_form": {
                        "observed_name": "copper",
                        "confidence": 1,
                        "source": "Inferlink Extraction v2"
                    },
                    "ore": {
                        "unit": {
                            "normalized_uri": "https://minmod.isi.edu/resource/Q202",
                            "observed_name": "million tonnes",
                            "confidence": 1,
                            "source": "Inferlink Extraction v2"
                        },
                        "value": 105.1
                    },
                    "grade": {
                        "unit": {
                            "normalized_uri": "https://minmod.isi.edu/resource/Q201",
                            "observed_name": "percent",
                            "confidence": 1,
                            "source": "Inferlink Extraction v2"
                        },
                        "value": 0.32
                    },
                    "cutoff_grade": {
                        "unit": {
                            "normalized_uri": "https://minmod.isi.edu/resource/Q204",
                            "observed_name": "percent Cu",
                            "confidence": 1,
                            "source": "Inferlink Extraction v2"
                        },
                        "value": 0.1
                    },
                    "contained_metal": 0.3363,
                    "reference": {
                        "document": {
                            "title": "NI 43-101 Technical Report for the Kinaskan Lake Project in North America dated May 2005.pdf",
                            "authors": [
                                "David T. Mehner",
                                "Giles R. Peatfield"
                            ],
                            "year": 2005,
                            "month": 5,
                            "description": "This technical report, prepared by consultants David T. Mehner and Giles R. Peatfield, provides an assessment of the Donnelly-GJ-North Copper-Gold Porphyry Zones in the Kinaskan Lake Project, including resource estimates and exploration recommendations.",
                            "uri": "https://api.cdr.land/v1/docs/documents/02df6bbca78257ce2e2bd47a455189e560508ad20fb695b32d1f882a99cd8badf0"
                        }
                    },
                    "date": "2005-5",
                    "zone": "donnelly zone"
                },
                {
                    "commodity": {
                        "normalized_uri": "https://minmod.isi.edu/resource/Q551",
                        "confidence": 1,
                        "source": "Inferlink Extraction v2"
                    },
                    "category": [
                        {
                            "normalized_uri": "https://minmod.isi.edu/resource/Inferred",
                            "confidence": 1,
                            "source": "Inferlink Extraction v2"
                        }
                    ],
                    "material_form": {
                        "observed_name": "copper",
                        "confidence": 1,
                        "source": "Inferlink Extraction v2"
                    },
                    "ore": {
                        "unit": {
                            "normalized_uri": "https://minmod.isi.edu/resource/Q202",
                            "observed_name": "million tonnes",
                            "confidence": 1,
                            "source": "Inferlink Extraction v2"
                        },
                        "value": 91.24
                    },
                    "grade": {
                        "unit": {
                            "normalized_uri": "https://minmod.isi.edu/resource/Q201",
                            "observed_name": "percent",
                            "confidence": 1,
                            "source": "Inferlink Extraction v2"
                        },
                        "value": 0.348
                    },
                    "cutoff_grade": {
                        "unit": {
                            "normalized_uri": "https://minmod.isi.edu/resource/Q204",
                            "observed_name": "percent Cu",
                            "confidence": 1,
                            "source": "Inferlink Extraction v2"
                        },
                        "value": 0.15
                    },
                    "contained_metal": 0.3175,
                    "reference": {
                        "document": {
                            "title": "NI 43-101 Technical Report for the Kinaskan Lake Project in North America dated May 2005.pdf",
                            "authors": [
                                "David T. Mehner",
                                "Giles R. Peatfield"
                            ],
                            "year": 2005,
                            "month": 5,
                            "description": "This technical report, prepared by consultants David T. Mehner and Giles R. Peatfield, provides an assessment of the Donnelly-GJ-North Copper-Gold Porphyry Zones in the Kinaskan Lake Project, including resource estimates and exploration recommendations.",
                            "uri": "https://api.cdr.land/v1/docs/documents/02df6bbca78257ce2e2bd47a455189e560508ad20fb695b32d1f882a99cd8badf0"
                        }
                    },
                    "date": "2005-5",
                    "zone": "donnelly zone"
                },
                {
                    "commodity": {
                        "normalized_uri": "https://minmod.isi.edu/resource/Q551",
                        "confidence": 1,
                        "source": "Inferlink Extraction v2"
                    },
                    "category": [
                        {
                            "normalized_uri": "https://minmod.isi.edu/resource/Inferred",
                            "confidence": 1,
                            "source": "Inferlink Extraction v2"
                        }
                    ],
                    "material_form": {
                        "observed_name": "copper",
                        "confidence": 1,
                        "source": "Inferlink Extraction v2"
                    },
                    "ore": {
                        "unit": {
                            "normalized_uri": "https://minmod.isi.edu/resource/Q202",
                            "observed_name": "million tonnes",
                            "confidence": 1,
                            "source": "Inferlink Extraction v2"
                        },
                        "value": 71.22
                    },
                    "grade": {
                        "unit": {
                            "normalized_uri": "https://minmod.isi.edu/resource/Q201",
                            "observed_name": "percent",
                            "confidence": 1,
                            "source": "Inferlink Extraction v2"
                        },
                        "value": 0.397
                    },
                    "cutoff_grade": {
                        "unit": {
                            "normalized_uri": "https://minmod.isi.edu/resource/Q204",
                            "observed_name": "percent Cu",
                            "confidence": 1,
                            "source": "Inferlink Extraction v2"
                        },
                        "value": 0.2
                    },
                    "contained_metal": 0.2827,
                    "reference": {
                        "document": {
                            "title": "NI 43-101 Technical Report for the Kinaskan Lake Project in North America dated May 2005.pdf",
                            "authors": [
                                "David T. Mehner",
                                "Giles R. Peatfield"
                            ],
                            "year": 2005,
                            "month": 5,
                            "description": "This technical report, prepared by consultants David T. Mehner and Giles R. Peatfield, provides an assessment of the Donnelly-GJ-North Copper-Gold Porphyry Zones in the Kinaskan Lake Project, including resource estimates and exploration recommendations.",
                            "uri": "https://api.cdr.land/v1/docs/documents/02df6bbca78257ce2e2bd47a455189e560508ad20fb695b32d1f882a99cd8badf0"
                        }
                    },
                    "date": "2005-5",
                    "zone": "donnelly zone"
                },
                {
                    "commodity": {
                        "normalized_uri": "https://minmod.isi.edu/resource/Q551",
                        "confidence": 1,
                        "source": "Inferlink Extraction v2"
                    },
                    "category": [
                        {
                            "normalized_uri": "https://minmod.isi.edu/resource/Inferred",
                            "confidence": 1,
                            "source": "Inferlink Extraction v2"
                        }
                    ],
                    "material_form": {
                        "observed_name": "copper",
                        "confidence": 1,
                        "source": "Inferlink Extraction v2"
                    },
                    "ore": {
                        "unit": {
                            "normalized_uri": "https://minmod.isi.edu/resource/Q202",
                            "observed_name": "million tonnes",
                            "confidence": 1,
                            "source": "Inferlink Extraction v2"
                        },
                        "value": 54.05
                    },
                    "grade": {
                        "unit": {
                            "normalized_uri": "https://minmod.isi.edu/resource/Q201",
                            "observed_name": "percent",
                            "confidence": 1,
                            "source": "Inferlink Extraction v2"
                        },
                        "value": 0.448
                    },
                    "cutoff_grade": {
                        "unit": {
                            "normalized_uri": "https://minmod.isi.edu/resource/Q204",
                            "observed_name": "percent Cu",
                            "confidence": 1,
                            "source": "Inferlink Extraction v2"
                        },
                        "value": 0.25
                    },
                    "contained_metal": 0.2421,
                    "reference": {
                        "document": {
                            "title": "NI 43-101 Technical Report for the Kinaskan Lake Project in North America dated May 2005.pdf",
                            "authors": [
                                "David T. Mehner",
                                "Giles R. Peatfield"
                            ],
                            "year": 2005,
                            "month": 5,
                            "description": "This technical report, prepared by consultants David T. Mehner and Giles R. Peatfield, provides an assessment of the Donnelly-GJ-North Copper-Gold Porphyry Zones in the Kinaskan Lake Project, including resource estimates and exploration recommendations.",
                            "uri": "https://api.cdr.land/v1/docs/documents/02df6bbca78257ce2e2bd47a455189e560508ad20fb695b32d1f882a99cd8badf0"
                        }
                    },
                    "date": "2005-5",
                    "zone": "donnelly zone"
                },
                {
                    "commodity": {
                        "normalized_uri": "https://minmod.isi.edu/resource/Q585",
                        "confidence": 1,
                        "source": "Inferlink Extraction v2"
                    },
                    "category": [
                        {
                            "normalized_uri": "https://minmod.isi.edu/resource/Inferred",
                            "confidence": 1,
                            "source": "Inferlink Extraction v2"
                        }
                    ],
                    "material_form": {
                        "observed_name": "silver",
                        "confidence": 1,
                        "source": "Inferlink Extraction v2"
                    },
                    "ore": {
                        "unit": {
                            "normalized_uri": "https://minmod.isi.edu/resource/Q202",
                            "observed_name": "million tonnes",
                            "confidence": 1,
                            "source": "Inferlink Extraction v2"
                        },
                        "value": 124.92
                    },
                    "grade": {
                        "unit": {
                            "normalized_uri": "https://minmod.isi.edu/resource/Q217",
                            "observed_name": "grams/tonne",
                            "confidence": 1,
                            "source": "Inferlink Extraction v2"
                        },
                        "value": 1.6
                    },
                    "cutoff_grade": {
                        "unit": {
                            "normalized_uri": "https://minmod.isi.edu/resource/Q204",
                            "observed_name": "percent Cu",
                            "confidence": 1,
                            "source": "Inferlink Extraction v2"
                        },
                        "value": 0.05
                    },
                    "contained_metal": 1.9987,
                    "reference": {
                        "document": {
                            "title": "NI 43-101 Technical Report for the Kinaskan Lake Project in North America dated May 2005.pdf",
                            "authors": [
                                "David T. Mehner",
                                "Giles R. Peatfield"
                            ],
                            "year": 2005,
                            "month": 5,
                            "description": "This technical report, prepared by consultants David T. Mehner and Giles R. Peatfield, provides an assessment of the Donnelly-GJ-North Copper-Gold Porphyry Zones in the Kinaskan Lake Project, including resource estimates and exploration recommendations.",
                            "uri": "https://api.cdr.land/v1/docs/documents/02df6bbca78257ce2e2bd47a455189e560508ad20fb695b32d1f882a99cd8badf0"
                        }
                    },
                    "date": "2005-5",
                    "zone": "donnelly zone"
                },
                {
                    "commodity": {
                        "normalized_uri": "https://minmod.isi.edu/resource/Q585",
                        "confidence": 1,
                        "source": "Inferlink Extraction v2"
                    },
                    "category": [
                        {
                            "normalized_uri": "https://minmod.isi.edu/resource/Inferred",
                            "confidence": 1,
                            "source": "Inferlink Extraction v2"
                        }
                    ],
                    "material_form": {
                        "observed_name": "silver",
                        "confidence": 1,
                        "source": "Inferlink Extraction v2"
                    },
                    "ore": {
                        "unit": {
                            "normalized_uri": "https://minmod.isi.edu/resource/Q202",
                            "observed_name": "million tonnes",
                            "confidence": 1,
                            "source": "Inferlink Extraction v2"
                        },
                        "value": 105.1
                    },
                    "grade": {
                        "unit": {
                            "normalized_uri": "https://minmod.isi.edu/resource/Q217",
                            "observed_name": "grams/tonne",
                            "confidence": 1,
                            "source": "Inferlink Extraction v2"
                        },
                        "value": 1.8
                    },
                    "cutoff_grade": {
                        "unit": {
                            "normalized_uri": "https://minmod.isi.edu/resource/Q204",
                            "observed_name": "percent Cu",
                            "confidence": 1,
                            "source": "Inferlink Extraction v2"
                        },
                        "value": 0.1
                    },
                    "contained_metal": 1.8918,
                    "reference": {
                        "document": {
                            "title": "NI 43-101 Technical Report for the Kinaskan Lake Project in North America dated May 2005.pdf",
                            "authors": [
                                "David T. Mehner",
                                "Giles R. Peatfield"
                            ],
                            "year": 2005,
                            "month": 5,
                            "description": "This technical report, prepared by consultants David T. Mehner and Giles R. Peatfield, provides an assessment of the Donnelly-GJ-North Copper-Gold Porphyry Zones in the Kinaskan Lake Project, including resource estimates and exploration recommendations.",
                            "uri": "https://api.cdr.land/v1/docs/documents/02df6bbca78257ce2e2bd47a455189e560508ad20fb695b32d1f882a99cd8badf0"
                        }
                    },
                    "date": "2005-5",
                    "zone": "donnelly zone"
                },
                {
                    "commodity": {
                        "normalized_uri": "https://minmod.isi.edu/resource/Q585",
                        "confidence": 1,
                        "source": "Inferlink Extraction v2"
                    },
                    "category": [
                        {
                            "normalized_uri": "https://minmod.isi.edu/resource/Inferred",
                            "confidence": 1,
                            "source": "Inferlink Extraction v2"
                        }
                    ],
                    "material_form": {
                        "observed_name": "silver",
                        "confidence": 1,
                        "source": "Inferlink Extraction v2"
                    },
                    "ore": {
                        "unit": {
                            "normalized_uri": "https://minmod.isi.edu/resource/Q202",
                            "observed_name": "million tonnes",
                            "confidence": 1,
                            "source": "Inferlink Extraction v2"
                        },
                        "value": 91.24
                    },
                    "grade": {
                        "unit": {
                            "normalized_uri": "https://minmod.isi.edu/resource/Q217",
                            "observed_name": "grams/tonne",
                            "confidence": 1,
                            "source": "Inferlink Extraction v2"
                        },
                        "value": 1.9
                    },
                    "cutoff_grade": {
                        "unit": {
                            "normalized_uri": "https://minmod.isi.edu/resource/Q204",
                            "observed_name": "percent Cu",
                            "confidence": 1,
                            "source": "Inferlink Extraction v2"
                        },
                        "value": 0.15
                    },
                    "contained_metal": 1.7336,
                    "reference": {
                        "document": {
                            "title": "NI 43-101 Technical Report for the Kinaskan Lake Project in North America dated May 2005.pdf",
                            "authors": [
                                "David T. Mehner",
                                "Giles R. Peatfield"
                            ],
                            "year": 2005,
                            "month": 5,
                            "description": "This technical report, prepared by consultants David T. Mehner and Giles R. Peatfield, provides an assessment of the Donnelly-GJ-North Copper-Gold Porphyry Zones in the Kinaskan Lake Project, including resource estimates and exploration recommendations.",
                            "uri": "https://api.cdr.land/v1/docs/documents/02df6bbca78257ce2e2bd47a455189e560508ad20fb695b32d1f882a99cd8badf0"
                        }
                    },
                    "date": "2005-5",
                    "zone": "donnelly zone"
                },
                {
                    "commodity": {
                        "normalized_uri": "https://minmod.isi.edu/resource/Q585",
                        "confidence": 1,
                        "source": "Inferlink Extraction v2"
                    },
                    "category": [
                        {
                            "normalized_uri": "https://minmod.isi.edu/resource/Inferred",
                            "confidence": 1,
                            "source": "Inferlink Extraction v2"
                        }
                    ],
                    "material_form": {
                        "observed_name": "silver",
                        "confidence": 1,
                        "source": "Inferlink Extraction v2"
                    },
                    "ore": {
                        "unit": {
                            "normalized_uri": "https://minmod.isi.edu/resource/Q202",
                            "observed_name": "million tonnes",
                            "confidence": 1,
                            "source": "Inferlink Extraction v2"
                        },
                        "value": 71.22
                    },
                    "grade": {
                        "unit": {
                            "normalized_uri": "https://minmod.isi.edu/resource/Q217",
                            "observed_name": "grams/tonne",
                            "confidence": 1,
                            "source": "Inferlink Extraction v2"
                        },
                        "value": 2.2
                    },
                    "cutoff_grade": {
                        "unit": {
                            "normalized_uri": "https://minmod.isi.edu/resource/Q204",
                            "observed_name": "percent Cu",
                            "confidence": 1,
                            "source": "Inferlink Extraction v2"
                        },
                        "value": 0.2
                    },
                    "contained_metal": 1.5668,
                    "reference": {
                        "document": {
                            "title": "NI 43-101 Technical Report for the Kinaskan Lake Project in North America dated May 2005.pdf",
                            "authors": [
                                "David T. Mehner",
                                "Giles R. Peatfield"
                            ],
                            "year": 2005,
                            "month": 5,
                            "description": "This technical report, prepared by consultants David T. Mehner and Giles R. Peatfield, provides an assessment of the Donnelly-GJ-North Copper-Gold Porphyry Zones in the Kinaskan Lake Project, including resource estimates and exploration recommendations.",
                            "uri": "https://api.cdr.land/v1/docs/documents/02df6bbca78257ce2e2bd47a455189e560508ad20fb695b32d1f882a99cd8badf0"
                        }
                    },
                    "date": "2005-5",
                    "zone": "donnelly zone"
                },
                {
                    "commodity": {
                        "normalized_uri": "https://minmod.isi.edu/resource/Q585",
                        "confidence": 1,
                        "source": "Inferlink Extraction v2"
                    },
                    "category": [
                        {
                            "normalized_uri": "https://minmod.isi.edu/resource/Inferred",
                            "confidence": 1,
                            "source": "Inferlink Extraction v2"
                        }
                    ],
                    "material_form": {
                        "observed_name": "silver",
                        "confidence": 1,
                        "source": "Inferlink Extraction v2"
                    },
                    "ore": {
                        "unit": {
                            "normalized_uri": "https://minmod.isi.edu/resource/Q202",
                            "observed_name": "million tonnes",
                            "confidence": 1,
                            "source": "Inferlink Extraction v2"
                        },
                        "value": 54.05
                    },
                    "grade": {
                        "unit": {
                            "normalized_uri": "https://minmod.isi.edu/resource/Q217",
                            "observed_name": "grams/tonne",
                            "confidence": 1,
                            "source": "Inferlink Extraction v2"
                        },
                        "value": 2.5
                    },
                    "cutoff_grade": {
                        "unit": {
                            "normalized_uri": "https://minmod.isi.edu/resource/Q204",
                            "observed_name": "percent Cu",
                            "confidence": 1,
                            "source": "Inferlink Extraction v2"
                        },
                        "value": 0.25
                    },
                    "contained_metal": 1.3513,
                    "reference": {
                        "document": {
                            "title": "NI 43-101 Technical Report for the Kinaskan Lake Project in North America dated May 2005.pdf",
                            "authors": [
                                "David T. Mehner",
                                "Giles R. Peatfield"
                            ],
                            "year": 2005,
                            "month": 5,
                            "description": "This technical report, prepared by consultants David T. Mehner and Giles R. Peatfield, provides an assessment of the Donnelly-GJ-North Copper-Gold Porphyry Zones in the Kinaskan Lake Project, including resource estimates and exploration recommendations.",
                            "uri": "https://api.cdr.land/v1/docs/documents/02df6bbca78257ce2e2bd47a455189e560508ad20fb695b32d1f882a99cd8badf0"
                        }
                    },
                    "date": "2005-5",
                    "zone": "donnelly zone"
                },
                {
                    "commodity": {
                        "normalized_uri": "https://minmod.isi.edu/resource/Q585",
                        "confidence": 1,
                        "source": "Inferlink Extraction v2"
                    },
                    "category": [
                        {
                            "normalized_uri": "https://minmod.isi.edu/resource/Inferred",
                            "confidence": 1,
                            "source": "Inferlink Extraction v2"
                        }
                    ],
                    "material_form": {
                        "observed_name": "silver",
                        "confidence": 1,
                        "source": "Inferlink Extraction v2"
                    },
                    "ore": {
                        "unit": {
                            "normalized_uri": "https://minmod.isi.edu/resource/Q202",
                            "observed_name": "million tonnes",
                            "confidence": 1,
                            "source": "Inferlink Extraction v2"
                        },
                        "value": 20.63
                    },
                    "grade": {
                        "unit": {
                            "normalized_uri": "https://minmod.isi.edu/resource/Q217",
                            "observed_name": "grams/tonne",
                            "confidence": 1,
                            "source": "Inferlink Extraction v2"
                        },
                        "value": 1.1
                    },
                    "cutoff_grade": {
                        "unit": {
                            "normalized_uri": "https://minmod.isi.edu/resource/Q204",
                            "observed_name": "percent Cu",
                            "confidence": 1,
                            "source": "Inferlink Extraction v2"
                        },
                        "value": 0.05
                    },
                    "contained_metal": 0.2269,
                    "reference": {
                        "document": {
                            "title": "NI 43-101 Technical Report for the Kinaskan Lake Project in North America dated May 2005.pdf",
                            "authors": [
                                "David T. Mehner",
                                "Giles R. Peatfield"
                            ],
                            "year": 2005,
                            "month": 5,
                            "description": "This technical report, prepared by consultants David T. Mehner and Giles R. Peatfield, provides an assessment of the Donnelly-GJ-North Copper-Gold Porphyry Zones in the Kinaskan Lake Project, including resource estimates and exploration recommendations.",
                            "uri": "https://api.cdr.land/v1/docs/documents/02df6bbca78257ce2e2bd47a455189e560508ad20fb695b32d1f882a99cd8badf0"
                        }
                    },
                    "date": "2005-5",
                    "zone": "nw sub-zone"
                },
                {
                    "commodity": {
                        "normalized_uri": "https://minmod.isi.edu/resource/Q585",
                        "confidence": 1,
                        "source": "Inferlink Extraction v2"
                    },
                    "category": [
                        {
                            "normalized_uri": "https://minmod.isi.edu/resource/Inferred",
                            "confidence": 1,
                            "source": "Inferlink Extraction v2"
                        }
                    ],
                    "material_form": {
                        "observed_name": "silver",
                        "confidence": 1,
                        "source": "Inferlink Extraction v2"
                    },
                    "ore": {
                        "unit": {
                            "normalized_uri": "https://minmod.isi.edu/resource/Q202",
                            "observed_name": "million tonnes",
                            "confidence": 1,
                            "source": "Inferlink Extraction v2"
                        },
                        "value": 17.79
                    },
                    "grade": {
                        "unit": {
                            "normalized_uri": "https://minmod.isi.edu/resource/Q217",
                            "observed_name": "grams/tonne",
                            "confidence": 1,
                            "source": "Inferlink Extraction v2"
                        },
                        "value": 1.2
                    },
                    "cutoff_grade": {
                        "unit": {
                            "normalized_uri": "https://minmod.isi.edu/resource/Q204",
                            "observed_name": "percent Cu",
                            "confidence": 1,
                            "source": "Inferlink Extraction v2"
                        },
                        "value": 0.1
                    },
                    "contained_metal": 0.2135,
                    "reference": {
                        "document": {
                            "title": "NI 43-101 Technical Report for the Kinaskan Lake Project in North America dated May 2005.pdf",
                            "authors": [
                                "David T. Mehner",
                                "Giles R. Peatfield"
                            ],
                            "year": 2005,
                            "month": 5,
                            "description": "This technical report, prepared by consultants David T. Mehner and Giles R. Peatfield, provides an assessment of the Donnelly-GJ-North Copper-Gold Porphyry Zones in the Kinaskan Lake Project, including resource estimates and exploration recommendations.",
                            "uri": "https://api.cdr.land/v1/docs/documents/02df6bbca78257ce2e2bd47a455189e560508ad20fb695b32d1f882a99cd8badf0"
                        }
                    },
                    "date": "2005-5",
                    "zone": "nw sub-zone"
                },
                {
                    "commodity": {
                        "normalized_uri": "https://minmod.isi.edu/resource/Q585",
                        "confidence": 1,
                        "source": "Inferlink Extraction v2"
                    },
                    "category": [
                        {
                            "normalized_uri": "https://minmod.isi.edu/resource/Inferred",
                            "confidence": 1,
                            "source": "Inferlink Extraction v2"
                        }
                    ],
                    "material_form": {
                        "observed_name": "silver",
                        "confidence": 1,
                        "source": "Inferlink Extraction v2"
                    },
                    "ore": {
                        "unit": {
                            "normalized_uri": "https://minmod.isi.edu/resource/Q202",
                            "observed_name": "million tonnes",
                            "confidence": 1,
                            "source": "Inferlink Extraction v2"
                        },
                        "value": 23.32
                    },
                    "grade": {
                        "unit": {
                            "normalized_uri": "https://minmod.isi.edu/resource/Q217",
                            "observed_name": "grams/tonne",
                            "confidence": 1,
                            "source": "Inferlink Extraction v2"
                        },
                        "value": 0.5
                    },
                    "cutoff_grade": {
                        "unit": {
                            "normalized_uri": "https://minmod.isi.edu/resource/Q204",
                            "observed_name": "percent Cu",
                            "confidence": 1,
                            "source": "Inferlink Extraction v2"
                        },
                        "value": 0.05
                    },
                    "contained_metal": 0.1166,
                    "reference": {
                        "document": {
                            "title": "NI 43-101 Technical Report for the Kinaskan Lake Project in North America dated May 2005.pdf",
                            "authors": [
                                "David T. Mehner",
                                "Giles R. Peatfield"
                            ],
                            "year": 2005,
                            "month": 5,
                            "description": "This technical report, prepared by consultants David T. Mehner and Giles R. Peatfield, provides an assessment of the Donnelly-GJ-North Copper-Gold Porphyry Zones in the Kinaskan Lake Project, including resource estimates and exploration recommendations.",
                            "uri": "https://api.cdr.land/v1/docs/documents/02df6bbca78257ce2e2bd47a455189e560508ad20fb695b32d1f882a99cd8badf0"
                        },
                        "page_info": [
                            {
                                "page": 50
                            }
                        ]
                    },
                    "date": "2005-5",
                    "zone": "sw sub-zone"
                }
            ],
            "deposit_type_candidate": [
                {
                    "observed_name": "copper-gold porphyry",
                    "normalized_uri": "https://minmod.isi.edu/resource/Q454",
                    "source": "Inferlink Extraction v2",
                    "confidence": 0.5
                },
                {
                    "observed_name": "gold-silver-copper-zinc bearing quartz veins",
                    "normalized_uri": "",
                    "source": "Inferlink Extraction v2",
                    "confidence": 0.5
                }
            ]
        }
    ]
}