{
  "MineralSite": [
    {
      "source_id": "https://w3id.org/usgs/z/4530692/RQ6P2GV7",
      "record_id": 1,
      "name": "NI 43-101 Technical Report for the Hakkari Project in Middle East, Turkey dated March 2010",
      "location_info": {
        "country": "https://minmod.isi.edu/resource/Q1227",
        "state_or_province": "https://minmod.isi.edu/resource/Q6373"
      },
      "mineral_inventory": [
        {
          "commodity": "https://minmod.isi.edu/resource/Q589",
          "reference": {
            "document": {
              "title": "NI 43-101 Technical Report for the Hakkari Project in Middle East, Turkey dated March 2010",
              "doi": "https://w3id.org/usgs/z/4530692/RQ6P2GV7",
              "authors": [
                "Mike Robertson",
                "Brendan Clarke"
              ],
              "year": 2010,
              "month": 3,
              "description": "This report provides an independent technical analysis of the Hakkari Zinc Project in Turkey, detailing the exploration licenses, geological setting, mineralization, and future recommendations for the project."
            }
          }
        }
      ],
      "deposit_type_candidate": [
        {
          "observed_name": "Non-sulphide zinc deposits",
          "normalized_uri": "https://minmod.isi.edu/resource/Q385",
          "source": "report",
          "confidence": 1.0
        }
      ]
    }
  ]
}